medthermal_dicom/__init__.py
medthermal_dicom/cli.py
medthermal_dicom/core.py
medthermal_dicom/metadata.py
medthermal_dicom/overlay.py
medthermal_dicom/utils.py
medthermal_dicom/visualization.py
medthermal_dicom-1.0.3.dist-info/licenses/LICENSE
medthermal_dicom-1.0.3.dist-info/METADATA
medthermal_dicom-1.0.3.dist-info/WHEEL
medthermal_dicom-1.0.3.dist-info/entry_points.txt
medthermal_dicom-1.0.3.dist-info/top_level.txt
medthermal_dicom-1.0.3.dist-info/RECORD
