Metadata-Version: 2.4
Name: medthermal-dicom
Version: 1.0.3
Summary: Professional thermal imaging DICOM library for medical applications
Author-email: "Niramai Health Analytix Pvt Ltd., Bangalore, India" <medthermaldicom@niramai.com>
License: MIT
Keywords: dicom,thermal,medical,imaging
Classifier: Development Status :: 5 - Production/Stable
Classifier: Intended Audience :: Science/Research
Classifier: License :: OSI Approved :: MIT License
Classifier: Operating System :: OS Independent
Classifier: Programming Language :: Python :: 3
Classifier: Programming Language :: Python :: 3.8
Classifier: Programming Language :: Python :: 3.9
Classifier: Programming Language :: Python :: 3.10
Classifier: Programming Language :: Python :: 3.11
Classifier: Topic :: Scientific/Engineering :: Image Processing
Requires-Python: >=3.8
License-File: LICENSE
Requires-Dist: pydicom>=2.3.0
Requires-Dist: numpy>=1.21.0
Requires-Dist: matplotlib>=3.5.0
Requires-Dist: opencv-python>=4.5.0
Requires-Dist: scipy>=1.7.0
Requires-Dist: pillow>=8.0.0
Requires-Dist: plotly>=5.0.0
Requires-Dist: dash>=2.0.0
Requires-Dist: dash-bootstrap-components>=1.0.0
Requires-Dist: pandas>=1.3.0
Provides-Extra: dev
Requires-Dist: pytest>=6.0; extra == "dev"
Requires-Dist: pytest-cov>=2.0; extra == "dev"
Requires-Dist: black>=21.0; extra == "dev"
Requires-Dist: flake8>=3.8; extra == "dev"
Requires-Dist: mypy>=0.910; extra == "dev"
Provides-Extra: docs
Requires-Dist: sphinx>=4.0; extra == "docs"
Requires-Dist: sphinx-rtd-theme>=1.0; extra == "docs"
Dynamic: license-file
